{"_type":"export","__export_format":4,"__export_date":"2024-07-31T22:31:32.794Z","__export_source":"insomnia.desktop.app:v9.3.3","resources":[{"_id":"req_0ec3545cf60f4db68d7a5751acc7802a","parentId":"fld_c3b67c4375364c10b66db51bb98217c1","modified":1722465033036,"created":1719519610976,"url":"{{ _.django_localhost }}/attendance/","name":"Create","description":"","method":"POST","body":{"mimeType":"application/json","text":"{\n\t\"student\": \"2\",\n\t\"lesson\": \"1\",\n\t\"status\": \"P\"\n}"},"parameters":[],"headers":[{"name":"Content-Type","value":"application/json"},{"name":"User-Agent","value":"insomnia/9.3.0"}],"authentication":{},"metaSortKey":-1719519610976,"isPrivate":false,"pathParameters":[],"settingStoreCookies":true,"settingSendCookies":true,"settingDisableRenderRequestBody":false,"settingEncodeUrl":true,"settingRebuildPath":true,"settingFollowRedirects":"global","_type":"request"},{"_id":"fld_c3b67c4375364c10b66db51bb98217c1","parentId":"wrk_0e863997b3494fe18fb636f2f23a8c16","modified":1719519206070,"created":1719519206070,"name":"Attendance","description":"","environment":{},"environmentPropertyOrder":null,"metaSortKey":-1719519206070,"_type":"request_group"},{"_id":"wrk_0e863997b3494fe18fb636f2f23a8c16","parentId":null,"modified":1722463203137,"created":1722463203137,"name":"Cursinho","description":"","scope":"collection","_type":"workspace"},{"_id":"req_95cff04c100b4c41b44d50ae59633a6e","parentId":"fld_c3b67c4375364c10b66db51bb98217c1","modified":1722464685116,"created":1719519409401,"url":"{{ _.django_localhost }}/lesson/1/update_attendance_registrability/","name":"Update Registrability","description":"","method":"PATCH","body":{},"parameters":[],"headers":[{"name":"User-Agent","value":"insomnia/9.3.0"}],"authentication":{},"metaSortKey":-1719519460174,"isPrivate":false,"pathParameters":[],"settingStoreCookies":true,"settingSendCookies":true,"settingDisableRenderRequestBody":false,"settingEncodeUrl":true,"settingRebuildPath":true,"settingFollowRedirects":"global","_type":"request"},{"_id":"req_d90fa4a874d640c59065939c10cc6d25","parentId":"fld_110f772dfb3c495cbda95f8f571c9553","modified":1716314663361,"created":1716305537991,"url":"{{ _.django_localhost }}/lesson/","name":"List Lesson","description":"","method":"GET","body":{},"parameters":[],"headers":[{"name":"User-Agent","value":"insomnia/9.2.0"}],"authentication":{},"preRequestScript":"","metaSortKey":-1716314577566,"isPrivate":false,"pathParameters":[],"settingStoreCookies":true,"settingSendCookies":true,"settingDisableRenderRequestBody":false,"settingEncodeUrl":true,"settingRebuildPath":true,"settingFollowRedirects":"global","_type":"request"},{"_id":"fld_110f772dfb3c495cbda95f8f571c9553","parentId":"wrk_0e863997b3494fe18fb636f2f23a8c16","modified":1716314202494,"created":1716314202494,"name":"Lesson (Aulas)","description":"","environment":{},"environmentPropertyOrder":null,"metaSortKey":-1716314202494,"_type":"request_group"},{"_id":"req_dba8788fa9014a4485548a006aaf14c0","parentId":"fld_110f772dfb3c495cbda95f8f571c9553","modified":1716314665327,"created":1716314222546,"url":"{{ _.django_localhost }}/lesson/1/","name":"Retrieve Lesson","description":"","method":"GET","body":{},"parameters":[],"headers":[{"name":"User-Agent","value":"insomnia/9.2.0"}],"authentication":{},"preRequestScript":"","metaSortKey":-1716314577516,"isPrivate":false,"pathParameters":[],"settingStoreCookies":true,"settingSendCookies":true,"settingDisableRenderRequestBody":false,"settingEncodeUrl":true,"settingRebuildPath":true,"settingFollowRedirects":"global","_type":"request"},{"_id":"req_19205c360e924610b8cc776fbc0757f1","parentId":"fld_110f772dfb3c495cbda95f8f571c9553","modified":1716314667779,"created":1716314257649,"url":"{{ _.django_localhost }}/lesson/","name":"Create Lesson","description":"","method":"POST","body":{"mimeType":"application/json","text":"{\n\t\"course_class\": \"1\",\n\t\"subject\": \"1\"\n}"},"parameters":[],"headers":[{"name":"Content-Type","value":"application/json"},{"name":"User-Agent","value":"insomnia/9.2.0"}],"authentication":{},"preRequestScript":"","metaSortKey":-1716314577491,"isPrivate":false,"pathParameters":[],"settingStoreCookies":true,"settingSendCookies":true,"settingDisableRenderRequestBody":false,"settingEncodeUrl":true,"settingRebuildPath":true,"settingFollowRedirects":"global","_type":"request"},{"_id":"req_461b897d59ab4eeda413b9e97217dbd7","parentId":"fld_110f772dfb3c495cbda95f8f571c9553","modified":1716314682627,"created":1716314577466,"url":"{{ _.django_localhost }}/lesson/2/","name":"Partial Edit Lesson","description":"","method":"PATCH","body":{"mimeType":"application/json","text":"{\n\t\"subject\": \"3\"\n}"},"parameters":[],"headers":[{"name":"Content-Type","value":"application/json"},{"name":"User-Agent","value":"insomnia/9.2.0"}],"authentication":{},"preRequestScript":"","metaSortKey":-1716314577466,"isPrivate":false,"pathParameters":[],"settingStoreCookies":true,"settingSendCookies":true,"settingDisableRenderRequestBody":false,"settingEncodeUrl":true,"settingRebuildPath":true,"settingFollowRedirects":"global","_type":"request"},{"_id":"req_963d7fc512214141bbcddb5897b0046d","parentId":"fld_110f772dfb3c495cbda95f8f571c9553","modified":1716314550131,"created":1716314493372,"url":"{{ _.django_localhost }}/lesson/1/","name":"Full Edit Lesson","description":"","method":"PUT","body":{"mimeType":"application/json","text":"{\n\t\"course_class\": \"1\",\n\t\"subject\": \"2\"\n}"},"parameters":[],"headers":[{"name":"Content-Type","value":"application/json"},{"name":"User-Agent","value":"insomnia/9.2.0"}],"authentication":{},"preRequestScript":"","metaSortKey":-1716314493372,"isPrivate":false,"pathParameters":[],"settingStoreCookies":true,"settingSendCookies":true,"settingDisableRenderRequestBody":false,"settingEncodeUrl":true,"settingRebuildPath":true,"settingFollowRedirects":"global","_type":"request"},{"_id":"req_af463e71a169434ca54036409190fcd4","parentId":"fld_110f772dfb3c495cbda95f8f571c9553","modified":1716314690755,"created":1716314627350,"url":"{{ _.django_localhost }}/lesson/1","name":"Destroy Lesson","description":"","method":"DELETE","body":{},"parameters":[],"headers":[{"name":"User-Agent","value":"insomnia/9.2.0"}],"authentication":{},"preRequestScript":"","metaSortKey":-1716314216645,"isPrivate":false,"pathParameters":[],"settingStoreCookies":true,"settingSendCookies":true,"settingDisableRenderRequestBody":false,"settingEncodeUrl":true,"settingRebuildPath":true,"settingFollowRedirects":"global","_type":"request"},{"_id":"env_4528eb63fe87423a956ea6299f64ad8d","parentId":"wrk_0e863997b3494fe18fb636f2f23a8c16","modified":1719521391135,"created":1716305512383,"name":"Base Environment","data":{"django_localhost":"http://localhost:8000"},"dataPropertyOrder":{"&":["django_localhost"]},"color":null,"isPrivate":false,"metaSortKey":1716305512383,"_type":"environment"},{"_id":"jar_c314da40beaf4c528525a518ae544655","parentId":"wrk_0e863997b3494fe18fb636f2f23a8c16","modified":1719521391122,"created":1716305512386,"name":"Default Jar","cookies":[],"_type":"cookie_jar"},{"_id":"env_2930122d5618486ebd95fc15e5a49dfe","parentId":"env_4528eb63fe87423a956ea6299f64ad8d","modified":1719521391130,"created":1716305609509,"name":"TCC","data":{},"dataPropertyOrder":{},"color":null,"isPrivate":false,"metaSortKey":1716305609509,"_type":"environment"}]}